{
  "type": "minecraft:generic",
  "pools": [
    {
      "rolls": { "min": 3, "max": 5 },
      "entries": [
        { "type": "minecraft:item", "name": "mekanism:alloy_infused", "weight": 30, "functions": [{ "function": "minecraft:set_count", "count": { "min": 8, "max": 24 } }] },
        { "type": "minecraft:item", "name": "mekanism:alloy_reinforced", "weight": 25, "functions": [{ "function": "minecraft:set_count", "count": { "min": 4, "max": 12 } }] },
        { "type": "minecraft:item", "name": "mekanism:alloy_atomic", "weight": 15, "functions": [{ "function": "minecraft:set_count", "count": { "min": 2, "max": 8 } }] },
        { "type": "minecraft:item", "name": "mekanism:elite_control_circuit", "weight": 20, "functions": [{ "function": "minecraft:set_count", "count": { "min": 4, "max": 8 } }] },
        { "type": "minecraft:item", "name": "mekanism:ultimate_control_circuit", "weight": 10, "functions": [{ "function": "minecraft:set_count", "count": { "min": 2, "max": 4 } }] }
      ]
    },
    {
      "rolls": { "min": 1, "max": 2 },
      "entries": [
        { "type": "minecraft:item", "name": "mekanism:basic_universal_cable", "weight": 30, "functions": [{ "function": "minecraft:set_count", "count": { "min": 32, "max": 64 } }] },
        { "type": "minecraft:item", "name": "mekanism:basic_mechanical_pipe", "weight": 25, "functions": [{ "function": "minecraft:set_count", "count": { "min": 16, "max": 32 } }] },
        { "type": "minecraft:item", "name": "mekanism:basic_logistical_transporter", "weight": 25, "functions": [{ "function": "minecraft:set_count", "count": { "min": 16, "max": 32 } }] },
        { "type": "minecraft:item", "name": "mekanism:basic_thermodynamic_conductor", "weight": 20, "functions": [{ "function": "minecraft:set_count", "count": { "min": 16, "max": 32 } }] }
      ]
    },
    {
      "rolls": 1,
      "entries": [
        { "type": "minecraft:item", "name": "mekanism:energy_tablet", "weight": 30, "functions": [{ "function": "minecraft:set_count", "count": { "min": 4, "max": 8 } }] },
        { "type": "minecraft:item", "name": "mekanism:configurator", "weight": 25 },
        { "type": "minecraft:item", "name": "mekanism:network_reader", "weight": 20 },
        { "type": "minecraft:item", "name": "mekanism:gauge_dropper", "weight": 25 }
      ]
    }
  ]
}
